<?xml version="1.0" encoding="UTF-8"?>
<con:soapui-project id="091239c9-b656-420b-9d5a-c291603c7cd7" activeEnvironment="Default" name="Dog API" resourceRoot="" soapui-version="5.5.0" xmlns:con="http://eviware.com/soapui/config"><con:settings/><con:interface xsi:type="con:RestService" id="87eaa441-d469-4950-a33e-2485d19e70da" wadlVersion="http://wadl.dev.java.net/2009/02" name="https://dog.ceo" type="rest" xmlns:xsi="http://www.w3.org/2001/XMLSchema-instance"><con:settings/><con:definitionCache type="TEXT" rootPart=""/><con:endpoints><con:endpoint>https://dog.ceo</con:endpoint></con:endpoints><con:resource name="All" path="/api/breeds/list/all" id="2b8c99b6-2909-4a9b-8820-a2b7f2422680"><con:settings/><con:parameters/><con:method name="GetAllDogs" id="d3ce422e-6bee-4e74-aaab-d347caabc939" method="GET"><con:settings/><con:parameters/><con:representation type="RESPONSE"><con:mediaType>application/json</con:mediaType><con:status>200</con:status><con:params/><con:element xmlns:all="https://dog.ceo/api/breeds/list/all">all:Response</con:element></con:representation><con:request name="getAllDogs Request" id="fccdd072-88e2-4cb9-899a-41e82d66b028" mediaType="application/json"><con:settings/><con:endpoint>https://dog.ceo</con:endpoint><con:parameters/></con:request></con:method></con:resource><con:resource name="list" path="/api/breed/{breedName}/list" id="9a3ea4d4-4ad1-4a5b-ac03-d417358549e2"><con:settings/><con:parameters><con:parameter><con:name>breedName</con:name><con:value>breedName</con:value><con:style>TEMPLATE</con:style><con:default>breedName</con:default></con:parameter><con:parameter><con:name/><con:style>QUERY</con:style></con:parameter><con:parameter><con:name>subBreed</con:name><con:style>QUERY</con:style></con:parameter></con:parameters><con:method name="GetSubBreed" id="79460f9e-492f-46a0-b758-65c2bd2058c2" method="GET"><con:settings/><con:parameters/><con:representation type="FAULT"><con:mediaType>application/json</con:mediaType><con:status>404</con:status><con:params/></con:representation><con:representation type="RESPONSE"><con:mediaType>application/json</con:mediaType><con:status>200</con:status><con:params/></con:representation><con:request name="getSubBreed Request" id="e3317d00-6aea-4ca9-b1ab-b12005b661b5" mediaType="application/json"><con:settings><con:setting id="com.eviware.soapui.impl.wsdl.WsdlRequest@request-headers">&lt;xml-fragment/></con:setting></con:settings><con:endpoint>https://dog.ceo</con:endpoint><con:request/><con:originalUri>https://dog.ceo/api/breed/breedName/list</con:originalUri><con:credentials><con:authType>No Authorization</con:authType></con:credentials><con:jmsConfig JMSDeliveryMode="PERSISTENT"/><con:jmsPropertyConfig/><con:parameters/><con:parameterOrder><con:entry>breedName</con:entry><con:entry>subBreed</con:entry></con:parameterOrder></con:request></con:method></con:resource><con:resource name="random" path="/api/breed/{breedName}/{subBreed}/images/random" id="ce06a291-3150-4c9b-b436-6f22eb87a79a"><con:settings/><con:parameters><con:parameter><con:name>breedName</con:name><con:style>TEMPLATE</con:style></con:parameter><con:parameter><con:name>subBreed</con:name><con:value>${#TestCase#subBreed}</con:value><con:style>QUERY</con:style><con:default>${#TestCase#subBreed}</con:default></con:parameter><con:parameter><con:name>subBreed</con:name><con:style>QUERY</con:style></con:parameter><con:parameter><con:name>breedName</con:name><con:style>TEMPLATE</con:style></con:parameter><con:parameter><con:name>subBreed</con:name><con:style>TEMPLATE</con:style></con:parameter></con:parameters><con:method name="GetRandomImage" id="ff94442e-9f91-4a76-9cd6-7ef61640e48f" method="GET"><con:settings/><con:parameters><con:parameter><con:name/><con:style>QUERY</con:style></con:parameter><con:parameter><con:name/><con:style>QUERY</con:style></con:parameter></con:parameters><con:representation type="RESPONSE"><con:mediaType>application/json</con:mediaType><con:status>200</con:status><con:params/><con:element xmlns:ran="https://dog.ceo/api/breeds/image/random">ran:Response</con:element></con:representation><con:representation type="FAULT"><con:mediaType>application/json</con:mediaType><con:status>404</con:status><con:params/><con:element xmlns:ran="https://dog.ceo/api/breed/%7D-/images/random">ran:Fault</con:element></con:representation><con:representation type="FAULT"><con:mediaType>text/html; charset=iso-8859-1</con:mediaType><con:status>404</con:status><con:params/><con:element>html</con:element></con:representation><con:request name="getRandomImage Request" id="60ea0a6a-74cb-48a1-8d2d-4b3f5ce4ffe4" mediaType="application/json"><con:settings><con:setting id="com.eviware.soapui.impl.wsdl.WsdlRequest@request-headers">&lt;xml-fragment/></con:setting></con:settings><con:endpoint>https://dog.ceo</con:endpoint><con:request/><con:originalUri>https://dog.ceo/api/breed/%7D-/images/random</con:originalUri><con:credentials><con:authType>No Authorization</con:authType></con:credentials><con:jmsConfig JMSDeliveryMode="PERSISTENT"/><con:jmsPropertyConfig/><con:parameters/><con:parameterOrder><con:entry>breedName</con:entry><con:entry>subBreed</con:entry></con:parameterOrder></con:request></con:method></con:resource></con:interface><con:testSuite id="881ad863-6338-4058-8227-ccca9fafd494" name="Dog API TestSuite"><con:settings/><con:runType>SEQUENTIAL</con:runType><con:testCase id="1114b0c2-caea-49d5-acdb-d406dc77b36b" failOnError="true" failTestCaseOnErrors="true" keepSession="false" maxResults="0" name="Dog API TestCase" searchProperties="true"><con:settings/><con:testStep type="restrequest" name="getAllDogRequest" id="5d8d2404-ca0f-4f66-a658-2266a0ac6232"><con:settings/><con:config service="https://dog.ceo" methodName="GetAllDogs" resourcePath="/api/breeds/list/all" xsi:type="con:RestRequestStep" xmlns:xsi="http://www.w3.org/2001/XMLSchema-instance"><con:restRequest name="getAllDogRequest" id="d4526a9f-9623-41d7-bd52-ad9f09eebc1d" mediaType="application/json"><con:settings><con:setting id="com.eviware.soapui.impl.wsdl.WsdlRequest@request-headers">&lt;xml-fragment/></con:setting></con:settings><con:encoding>UTF-8</con:encoding><con:endpoint>https://dog.ceo</con:endpoint><con:request/><con:originalUri>https://dog.ceo/api/breeds/list/all</con:originalUri><con:assertion type="Valid HTTP Status Codes" id="9cda7160-659d-4a76-a2dc-194b99cfef21" name="Valid HTTP Status Codes"><con:configuration><codes>200</codes></con:configuration></con:assertion><con:credentials><con:authType>No Authorization</con:authType></con:credentials><con:jmsConfig JMSDeliveryMode="PERSISTENT"/><con:jmsPropertyConfig/><con:parameters/></con:restRequest></con:config></con:testStep><con:testStep type="groovy" name="ValidateBreedExists" id="c8b0c4b6-8101-4a30-8c75-922b0d4e6984"><con:settings/><con:config><script>import groovy.json.JsonSlurper

responseContent = testRunner.testCase.getTestStepByName("getAllDogRequest").getPropertyValue("response")
slurperresponse = new JsonSlurper().parseText(responseContent)
response = (slurperresponse.message).toString()
assert response.contains(testRunner.testCase.getPropertyValue("breedName"))
log.info (response)</script></con:config></con:testStep><con:testStep type="restrequest" name="getSubBreedRequst" id="1bacbdfa-0444-4882-b80f-3fa663990ddc"><con:settings/><con:config service="https://dog.ceo" resourcePath="/api/breed/{breedName}/list" methodName="GetSubBreed" xsi:type="con:RestRequestStep" xmlns:xsi="http://www.w3.org/2001/XMLSchema-instance"><con:restRequest name="getSubBreedRequst" id="e3317d00-6aea-4ca9-b1ab-b12005b661b5" mediaType="application/json"><con:settings><con:setting id="com.eviware.soapui.impl.wsdl.WsdlRequest@request-headers">&lt;xml-fragment/></con:setting></con:settings><con:endpoint>https://dog.ceo</con:endpoint><con:request/><con:originalUri>https://dog.ceo/api/breed//list</con:originalUri><con:assertion type="Valid HTTP Status Codes" id="6a6a6cba-e531-4ba7-acca-db0e37aef256" name="Valid HTTP Status Codes"><con:configuration><codes>200</codes></con:configuration></con:assertion><con:credentials><con:authType>No Authorization</con:authType></con:credentials><con:jmsConfig JMSDeliveryMode="PERSISTENT"/><con:jmsPropertyConfig/><con:parameters><entry key="breedName" value="${#TestCase#breedName}" xmlns="http://eviware.com/soapui/config"/></con:parameters><con:parameterOrder><con:entry>breedName</con:entry><con:entry>subBreed</con:entry></con:parameterOrder></con:restRequest></con:config></con:testStep><con:testStep type="transfer" name="transferSubBreed" id="4ab4191f-2e55-438c-ae5b-235e1f06bae2"><con:settings/><con:config xsi:type="con:PropertyTransfersStep" xmlns:xsi="http://www.w3.org/2001/XMLSchema-instance"><con:transfers setNullOnMissingSource="true" transferTextContent="true" failOnError="true" ignoreEmpty="false" transferToAll="false" entitize="false" transferChildNodes="false" disabled="false"><con:name>subBreedName</con:name><con:sourceType>Response</con:sourceType><con:sourceStep>getSubBreedRequst</con:sourceStep><con:sourcePath>message.[3]</con:sourcePath><con:targetType>subBreed</con:targetType><con:targetStep>#TestCase#</con:targetStep><con:type>JSONPATH</con:type><con:targetTransferType>JSONPATH</con:targetTransferType><con:upgraded>true</con:upgraded></con:transfers></con:config></con:testStep><con:testStep type="restrequest" name="GetRandomImage" id="6d27b395-a256-4b7a-aa7b-fcdcd994123d"><con:settings/><con:config service="https://dog.ceo" resourcePath="/api/breed/{breedName}/{subBreed}/images/random" methodName="GetRandomImage" xsi:type="con:RestRequestStep" xmlns:xsi="http://www.w3.org/2001/XMLSchema-instance"><con:restRequest name="GetRandomImage" id="60ea0a6a-74cb-48a1-8d2d-4b3f5ce4ffe4" mediaType="application/json"><con:settings><con:setting id="com.eviware.soapui.impl.wsdl.WsdlRequest@request-headers">&lt;xml-fragment/></con:setting></con:settings><con:endpoint>https://dog.ceo</con:endpoint><con:request/><con:originalUri>https://dog.ceo/api/breed/%7D-/images/random</con:originalUri><con:assertion type="Valid HTTP Status Codes" id="e32930f0-23a4-45d4-ab42-9748079baf47" name="Valid HTTP Status Codes"><con:configuration><codes>200</codes></con:configuration></con:assertion><con:credentials><con:authType>No Authorization</con:authType></con:credentials><con:jmsConfig JMSDeliveryMode="PERSISTENT"/><con:jmsPropertyConfig/><con:parameters>
  <con:entry key="breedName" value="${#TestCase#breedName}"/>
  <con:entry key="subBreed" value="${#TestCase#subBreed}"/>
</con:parameters><con:parameterOrder><con:entry>breedName</con:entry><con:entry>subBreed</con:entry></con:parameterOrder></con:restRequest></con:config></con:testStep><con:testStep type="groovy" name="ValidateImageContainsGolden" id="99443d13-c3f4-4fc2-9487-a8d04ff01ba9"><con:settings/><con:config><script/></con:config></con:testStep><con:properties><con:property><con:name>breedName</con:name><con:value>retriever</con:value></con:property><con:property><con:name>subBreed</con:name><con:value>golden</con:value></con:property></con:properties></con:testCase><con:properties/></con:testSuite><con:properties/><con:wssContainer/><con:oAuth2ProfileContainer/><con:oAuth1ProfileContainer/><con:sensitiveInformation/></con:soapui-project>